OpenLane/testing_designs/clk_generator/clk_gen.v
`timescale 1ns/1ps

module clk_gen(
    input enable,
    output reg clk);

    parameter FREQ = 100000;    // in kHz
    parameter PHASE = 0;        // in degrees
    parameter DUTY = 50;        // in percentage

    real clk_pd;
    real clk_on;
    real clk_off;
    real quarter;
    real start_dly;

    reg start_clk;

    always @ (FREQ, DUTY, PHASE) begin
        clk_pd = 1.0/(FREQ * 1e3) * 1e9;   // convert to ns
        clk_on = DUTY/100.0 * clk_pd;
        clk_off = (100.0 - DUTY)/100.0 * clk_pd;
        quarter = clk_pd / 4 ;
        start_dly = quarter * PHASE / 90;
    end

    initial begin
        $display("FREQ      = %0d kHz", FREQ);
        $display("PHASE     = %0d deg", PHASE);
        $display("DUTY      = %0d %%", DUTY);

        $display("PERIOD    = %0.3f ns", clk_pd);
        $display("CLK_ON    = %0.3f ns", clk_on);
        $display("CLK_OFF   = %0.3f ns", clk_off);
        $display("QUARTER   = %0.3f ns", quarter);
        $display("START_DLY = %0.3f ns", start_dly);
    end

    // Inicializar variables en cero
    initial begin
        clk <= 0;
        start_clk <= 0;
    end

    // When clock is enabled, delay driving the clock to one 
    // in order to achieve the phase effect. start_dly is configured 
    // to the correct delay for the configured phase. 
    // When enable is 0, allow enough time to complete the current clock period.
    always @(posedge enable or negedge enable) begin
        if (enable) begin
            #(start_dly) start_clk = 1;
        end else begin
            #(start_dly) start_clk = 0;
        end
    end

    // Achieve duty cycle by a skewed clock on/off time and let this run as 
    // long as the clocks are turned off
    always @(posedge start_clk) begin
        if (start_clk) begin
            clk = 1;
            while (start_clk) begin
                #(clk_on) clk = 0;
                #(clk_off) clk = 1;
            end        
            clk = 0;
        end
    end

endmodule

OpenLane/testing_designs/clk_generator/tb_clk_gen.v
// tb_clk_gen.v
module tb;
    wire clk1,clk2,clk3,clk4,clk5,clk6,clk7,clk8;

    reg enable;
    reg [7:0] dly;

    // Instancias del generador de reloj
    clk_gen u1( .enable(enable), .clk(clk1));
    clk_gen #(.FREQ(200000)) u2(.enable(enable), .clk(clk2));
    clk_gen #(.FREQ(400000)) u3(.enable(enable), .clk(clk3));
    clk_gen #(.FREQ(60000)) u4(.enable(enable), .clk(clk4));
    clk_gen #(.FREQ(50000)) u5(.enable(enable), .clk(clk5));
    clk_gen #(.FREQ(50000), .PHASE(45)) u6(.enable(enable), .clk(clk6));
    clk_gen #(.FREQ(50000), .PHASE(90)) u7(.enable(enable), .clk(clk7));
    clk_gen #(.FREQ(50000), .PHASE(180)) u8(.enable(enable), .clk(clk8));

    initial begin 
        $dumpfile("wf_clk_gen.vcd");
        $dumpvars(0, tb);
        enable <= 0;

        for (integer i = 0; i < 10; i = i + 1) begin
            dly = $random;
            #(dly) enable <= ~enable;
            $display("i=%0d dly=%0d", i, dly);
            #50;
        end

        #50 $finish;
    end
endmodule

OpenLane/testing_designs/clk_generator/wf_clk_gen.vcd
$date
	Wed Jun 12 21:37:50 2024
$end
$version
	Icarus Verilog
$end
$timescale
	1s
$end
$scope module tb $end
$var wire 1 ! clk8 $end
$var wire 1 " clk7 $end
$var wire 1 # clk6 $end
$var wire 1 $ clk5 $end
$var wire 1 % clk4 $end
$var wire 1 & clk3 $end
$var wire 1 ' clk2 $end
$var wire 1 ( clk1 $end
$var reg 8 ) dly [7:0] $end
$var reg 1 * enable $end
$scope module u1 $end
$var wire 1 * enable $end
$var reg 1 ( clk $end
$var reg 1 + start_clk $end
$var real 1 , clk_off $end
$var real 1 - clk_on $end
$var real 1 . clk_pd $end
$var real 1 / quarter $end
$var real 1 0 start_dly $end
$upscope $end
$scope module u2 $end
$var wire 1 * enable $end
$var reg 1 ' clk $end
$var reg 1 1 start_clk $end
$var real 1 2 clk_off $end
$var real 1 3 clk_on $end
$var real 1 4 clk_pd $end
$var real 1 5 quarter $end
$var real 1 6 start_dly $end
$upscope $end
$scope module u3 $end
$var wire 1 * enable $end
$var reg 1 & clk $end
$var reg 1 7 start_clk $end
$var real 1 8 clk_off $end
$var real 1 9 clk_on $end
$var real 1 : clk_pd $end
$var real 1 ; quarter $end
$var real 1 < start_dly $end
$upscope $end
$scope module u4 $end
$var wire 1 * enable $end
$var reg 1 % clk $end
$var reg 1 = start_clk $end
$var real 1 > clk_off $end
$var real 1 ? clk_on $end
$var real 1 @ clk_pd $end
$var real 1 A quarter $end
$var real 1 B start_dly $end
$upscope $end
$scope module u5 $end
$var wire 1 * enable $end
$var reg 1 $ clk $end
$var reg 1 C start_clk $end
$var real 1 D clk_off $end
$var real 1 E clk_on $end
$var real 1 F clk_pd $end
$var real 1 G quarter $end
$var real 1 H start_dly $end
$upscope $end
$scope module u6 $end
$var wire 1 * enable $end
$var reg 1 # clk $end
$var reg 1 I start_clk $end
$var real 1 J clk_off $end
$var real 1 K clk_on $end
$var real 1 L clk_pd $end
$var real 1 M quarter $end
$var real 1 N start_dly $end
$upscope $end
$scope module u7 $end
$var wire 1 * enable $end
$var reg 1 " clk $end
$var reg 1 O start_clk $end
$var real 1 P clk_off $end
$var real 1 Q clk_on $end
$var real 1 R clk_pd $end
$var real 1 S quarter $end
$var real 1 T start_dly $end
$upscope $end
$scope module u8 $end
$var wire 1 * enable $end
$var reg 1 ! clk $end
$var reg 1 U start_clk $end
$var real 1 V clk_off $end
$var real 1 W clk_on $end
$var real 1 X clk_pd $end
$var real 1 Y quarter $end
$var real 1 Z start_dly $end
$upscope $end
$scope begin $ivl_for_loop0 $end
$var integer 32 [ i [31:0] $end
$upscope $end
$upscope $end
$enddefinitions $end
#0
$dumpvars
b0 [
r10 Z
r5 Y
r20 X
r10 W
r10 V
0U
r5 T
r5 S
r20 R
r10 Q
r10 P
0O
r2.5 N
r5 M
r20 L
r10 K
r10 J
0I
r0 H
r5 G
r20 F
r10 E
r10 D
0C
r0 B
r4.166666666666667 A
r16.66666666666667 @
r8.333333333333334 ?
r8.333333333333334 >
0=
r0 <
r0.625 ;
r2.5 :
r1.25 9
r1.25 8
07
r0 6
r1.25 5
r5 4
r2.5 3
r2.5 2
01
r0 0
r2.5 /
r10 .
r5 -
r5 ,
0+
0*
b100100 )
0(
0'
0&
0%
0$
0#
0"
0!
$end
#36
1$
1%
1&
1'
1(
1C
1=
17
11
1+
1*
#37
0&
#38
1&
#39
1#
0&
0'
1I
#40
1&
#41
1"
0&
0(
1O
#42
1&
1'
#43
0&
#44
1&
0%
#45
0&
0'
#46
1!
1&
1(
0$
1U
#47
0&
#48
1&
1'
#49
0&
0#
#50
1&
#51
0&
0'
0(
0"
#52
1&
1%
#53
0&
#54
1&
1'
#55
0&
#56
1&
1(
0!
1$
#57
0&
0'
#58
1&
#59
0&
1#
#60
1&
1'
0%
#61
0&
0(
1"
#62
1&
#63
0&
0'
#64
1&
#65
0&
#66
1&
1'
1(
1!
0$
#67
0&
#68
1&
1%
#69
0&
0'
0#
#70
1&
#71
0&
0(
0"
#72
1&
1'
#73
0&
#74
1&
#75
0&
0'
#76
1&
1(
0%
0!
1$
#77
0&
#78
1&
1'
#79
0&
1#
#80
1&
#81
0&
0'
0(
1"
#82
1&
#83
0&
#84
1&
1'
1%
#85
0&
#86
1&
1(
1!
0$
b10000001 )
b1 [
#87
0&
0'
#88
1&
#89
0&
0#
#90
1&
1'
#91
0&
0(
0"
#92
1&
0%
#93
0&
0'
#94
1&
#95
0&
#96
1&
1'
1(
0!
1$
#97
0&
#98
1&
#99
0&
0'
1#
#100
1&
1%
#101
0&
0(
1"
#102
1&
1'
#103
0&
#104
1&
#105
0&
0'
#106
1&
1(
1!
0$
#107
0&
#108
1&
1'
0%
#109
0&
0#
#110
1&
#111
0&
0'
0(
0"
#112
1&
#113
0&
#114
1&
1'
#115
0&
#116
1&
1(
1%
0!
1$
#117
0&
0'
#118
1&
#119
0&
1#
#120
1&
1'
#121
0&
0(
1"
#122
1&
#123
0&
0'
#124
1&
0%
#125
0&
#126
1&
1'
1(
1!
0$
#127
0&
#128
1&
#129
0&
0'
0#
#130
1&
#131
0&
0(
0"
#132
1&
1'
1%
#133
0&
#134
1&
#135
0&
0'
#136
1&
1(
0!
1$
#137
0&
#138
1&
1'
#139
0&
1#
#140
1&
0%
#141
0&
0'
0(
1"
#142
1&
#143
0&
#144
1&
1'
#145
0&
#146
1&
1(
1!
0$
#147
0&
0'
#148
1&
1%
#149
0&
0#
#150
1&
1'
#151
0&
0(
0"
#152
1&
#153
0&
0'
#154
1&
#155
0&
#156
1&
1'
1(
0%
0!
1$
#157
0&
#158
1&
#159
0&
0'
1#
#160
1&
#161
0&
0(
1"
#162
1&
1'
#163
0&
#164
1&
1%
#165
0&
0'
#166
1&
1(
1!
0$
#167
0&
#168
1&
1'
#169
0&
0#
#170
1&
#171
0&
0'
0(
0"
#172
1&
0%
#173
0&
#174
1&
1'
#175
0&
#176
1&
1(
0!
1$
#177
0&
0'
#178
1&
#179
0&
1#
#180
1&
1'
1%
#181
0&
0(
1"
#182
1&
#183
0&
0'
#184
1&
#185
0&
#186
1&
1'
1(
1!
0$
#187
0&
#188
1&
0%
#189
0&
0'
0#
#190
1&
#191
0&
0(
0"
#192
1&
1'
#193
0&
#194
1&
#195
0&
0'
#196
1&
1(
1%
0!
1$
#197
0&
#198
1&
1'
#199
0&
1#
#200
1&
#201
0&
0'
0(
1"
#202
1&
#203
0&
#204
1&
1'
0%
#205
0&
#206
1&
1(
1!
0$
#207
0&
0'
#208
1&
#209
0&
0#
#210
1&
1'
#211
0&
0(
0"
#212
1&
1%
#213
0&
0'
#214
1&
#215
0+
01
07
0=
0C
0*
0&
#216
0&
0'
0(
0!
0$
#218
0I
#219
0#
#220
0O
0%
#221
0"
#225
0U
#226
0!
#228
0%
#265
b1001 )
b10 [
#274
1$
1%
1&
1'
1(
1C
1=
17
11
1+
1*
#275
0&
#276
1&
#277
1#
0&
0'
1I
#278
1&
#279
1"
0&
0(
1O
#280
1&
1'
#281
0&
#282
1&
0%
#283
0&
0'
#284
1!
1&
1(
0$
1U
#285
0&
#286
1&
1'
#287
0&
0#
#288
1&
#289
0&
0'
0(
0"
#290
1&
1%
#291
0&
#292
1&
1'
#293
0&
#294
1&
1(
0!
1$
#295
0&
0'
#296
1&
#297
0&
1#
#298
1&
1'
0%
#299
0&
0(
1"
#300
1&
#301
0&
0'
#302
1&
#303
0&
#304
1&
1'
1(
1!
0$
#305
0&
#306
1&
1%
#307
0&
0'
0#
#308
1&
#309
0&
0(
0"
#310
1&
1'
#311
0&
#312
1&
#313
0&
0'
#314
1&
1(
0%
0!
1$
#315
0&
#316
1&
1'
#317
0&
1#
#318
1&
#319
0&
0'
0(
1"
#320
1&
#321
0&
#322
1&
1'
1%
#323
0&
#324
1&
1(
1!
0$
b1100011 )
b11 [
#325
0&
0'
#326
1&
#327
0&
0#
#328
1&
1'
#329
0&
0(
0"
#330
1&
0%
#331
0&
0'
#332
1&
#333
0&
#334
1&
1'
1(
0!
1$
#335
0&
#336
1&
#337
0&
0'
1#
#338
1&
1%
#339
0&
0(
1"
#340
1&
1'
#341
0&
#342
1&
#343
0&
0'
#344
1&
1(
1!
0$
#345
0&
#346
1&
1'
0%
#347
0&
0#
#348
1&
#349
0&
0'
0(
0"
#350
1&
#351
0&
#352
1&
1'
#353
0&
#354
1&
1(
1%
0!
1$
#355
0&
0'
#356
1&
#357
0&
1#
#358
1&
1'
#359
0&
0(
1"
#360
1&
#361
0&
0'
#362
1&
0%
#363
0&
#364
1&
1'
1(
1!
0$
#365
0&
#366
1&
#367
0&
0'
0#
#368
1&
#369
0&
0(
0"
#370
1&
1'
1%
#371
0&
#372
1&
#373
0&
0'
#374
1&
1(
0!
1$
#375
0&
#376
1&
1'
#377
0&
1#
#378
1&
0%
#379
0&
0'
0(
1"
#380
1&
#381
0&
#382
1&
1'
#383
0&
#384
1&
1(
1!
0$
#385
0&
0'
#386
1&
1%
#387
0&
0#
#388
1&
1'
#389
0&
0(
0"
#390
1&
#391
0&
0'
#392
1&
#393
0&
#394
1&
1'
1(
0%
0!
1$
#395
0&
#396
1&
#397
0&
0'
1#
#398
1&
#399
0&
0(
1"
#400
1&
1'
#401
0&
#402
1&
1%
#403
0&
0'
#404
1&
1(
1!
0$
#405
0&
#406
1&
1'
#407
0&
0#
#408
1&
#409
0&
0'
0(
0"
#410
1&
0%
#411
0&
#412
1&
1'
#413
0&
#414
1&
1(
0!
1$
#415
0&
0'
#416
1&
#417
0&
1#
#418
1&
1'
1%
#419
0&
0(
1"
#420
1&
#421
0&
0'
#422
1&
#423
0+
01
07
0=
0C
0*
0&
#424
0&
0'
0(
1!
0$
#426
0I
0%
#427
0#
#428
0O
#429
0"
#433
0U
#434
0%
0!
0$
#437
0#
#439
0"
#444
0!
#473
b1101 )
b100 [
#486
1$
1%
1&
1'
1(
1C
1=
17
11
1+
1*
