OpenLane/testing_designs/signal_generator/signal_generator.v
module signal_generator (
    input wire clk,          // Reloj principal
    input wire [3:0] sel,    // Entrada de 4 bits para seleccionar el periodo de phi_p
    output reg phi_l1,       // Señal phi_l1
    output reg phi_l2,       // Señal phi_l2
    output reg phi_p,        // Señal phi_p
    output reg phi_r         // Señal phi_r
);

// Contadores
reg [5:0] l_counter = 0;      // Contador para phi_l1 y phi_l2 (6 ciclos)
reg [13:0] p_counter = 0;     // Contador para phi_p (mínimo 1048 ciclos)
reg [5:0] r_counter = 0;      // Contador para phi_r (mitad del duty cycle de phi_l2)

// Constantes
parameter MIN_P_CYCLES = 1048;  // Mínimo de ciclos para phi_p

always @(posedge clk) begin
    // Generar phi_l1 y phi_l2
    if (l_counter == 6) begin
        phi_l1 <= ~phi_l1;
        phi_l2 <= ~phi_l2;
        l_counter <= 0;
    end else begin
        l_counter <= l_counter + 1;
    end

    // Generar phi_p
    if (phi_l1 == 1'b1) begin
        if (p_counter >= (MIN_P_CYCLES + sel)) begin
            phi_p <= 1'b1;
            p_counter <= 0;
        end else begin
            phi_p <= 1'b0;
            p_counter <= p_counter + 1;
        end
    end

    // Generar phi_r (mitad del duty cycle de phi_l2)
    if (r_counter >= 3) begin
        phi_r <= ~phi_r;
        r_counter <= 0;
    end else begin
        r_counter <= r_counter + 1;
    end
end

endmodule

OpenLane/desings/src/signal_generator/tb_signal_generator.v
`timescale 1ns / 1ps

module test_signal_generator;

    // Declaring the signals
    reg clk;
    reg [3:0] sel;
    wire phi_l1, phi_l2, phi_p, phi_r;

    // Instantiate the Unit Under Test (UUT)
    signal_generator uut (
        .clk(clk), 
        .sel(sel), 
        .phi_l1(phi_l1), 
        .phi_l2(phi_l2), 
        .phi_p(phi_p), 
        .phi_r(phi_r)
    );

    initial begin
            $dumpfile("wf_signal_generatir.vcd");
        $dumpvars(0, test_signal_generator);
        // Initialize Inputs
        clk = 0;
        sel = 4'b0000;

        // Wait 100 ns for global reset to finish
        #100;
        
        // Add stimulus here
        sel = 4'b1010;
        #100;
        sel = 4'b0101;
        #100;
    $finish; // Terminar la simulación
    end

    // Mostrar resultados en cada cambio de reloj
    //always @(posedge clk) begin
        //$display("Time: %d, max_val: %b, count: %d, phi_p: %b, phi_l1: %b, phi_l2: %b, phi_r: %b", $time, max_val, uut.count, phi_p, phi_l1, phi_l2, phi_r);
    //end
      
    // Clock Generation
    always #10 clk = ~clk;

endmodule

OpenLane/testing_designs/signal_generator/wf_signal_generatir.vcd
$date
	Wed Jun 12 22:01:54 2024
$end
$version
	Icarus Verilog
$end
$timescale
	1ps
$end
$scope module test_signal_generator $end
$var wire 1 ! phi_r $end
$var wire 1 " phi_p $end
$var wire 1 # phi_l2 $end
$var wire 1 $ phi_l1 $end
$var reg 1 % clk $end
$var reg 4 & sel [3:0] $end
$scope module uut $end
$var wire 1 % clk $end
$var wire 4 ' sel [3:0] $end
$var reg 6 ( l_counter [5:0] $end
$var reg 14 ) p_counter [13:0] $end
$var reg 1 $ phi_l1 $end
$var reg 1 # phi_l2 $end
$var reg 1 " phi_p $end
$var reg 1 ! phi_r $end
$var reg 6 * r_counter [5:0] $end
$upscope $end
$upscope $end
$enddefinitions $end
#0
$dumpvars
b0 *
b0 )
b0 (
b0 '
b0 &
0%
x$
x#
x"
x!
$end
#10000
b1 *
b1 (
1%
#20000
0%
#30000
b10 *
b10 (
1%
#40000
0%
#50000
b11 *
b11 (
1%
#60000
0%
#70000
b0 *
b100 (
1%
#80000
0%
#90000
b1 *
b101 (
1%
#100000
0%
b1010 &
b1010 '
#110000
b10 *
b110 (
1%
#120000
0%
#130000
b11 *
b0 (
1%
#140000
0%
#150000
b0 *
b1 (
1%
#160000
0%
#170000
b1 *
b10 (
1%
#180000
0%
#190000
b10 *
b11 (
1%
#200000
0%
b101 &
b101 '
#210000
b11 *
b100 (
1%
#220000
0%
#230000
b0 *
b101 (
1%
#240000
0%
#250000
b1 *
b110 (
1%
#260000
0%
#270000
b10 *
b0 (
1%
#280000
0%
#290000
b11 *
b1 (
1%
