OpenLane/testing_designs/pulse_generator/pulse_generator.v
module pulse_generator(
    input clk,
    input rst,
    input [3:0] DIVIDE_BY_N,
    output comb_out, 
    output reg sync_out
);

reg [10:0] count = 0; // Corregir la declaración del vector

always @(posedge clk) begin
    if (rst) begin
        count <= 0;
    end else if (count < DIVIDE_BY_N-1) begin
        count <= count + 1;
    end else begin
        count <= 0;
    end
end

// Salida combinacional
assign comb_out = (count == DIVIDE_BY_N-1) ? 1'b1 : 1'b0;

// Salida sincrónica
always @(posedge clk) begin
    sync_out <= (count == DIVIDE_BY_N-1) ? 1'b1 : 1'b0;
end

endmodule

OpenLane/desings/src/pulse_generator/pulse_generator_tb.v
`timescale 1ns / 1ps

module tb_pulse_generator;

    // Entradas
    reg clk;
    reg rst;
    reg [3:0] DIVIDE_BY_N;

    // Salidas
    wire comb_out;
    wire sync_out;

    // Instancia del módulo a probar
    pulse_generator uut (
        .clk(clk), 
        .rst(rst), 
        .DIVIDE_BY_N(DIVIDE_BY_N), 
        .comb_out(comb_out), 
        .sync_out(sync_out)
    );

    // Generación del reloj
    initial begin
        clk = 0;
        forever #5 clk = ~clk; // Periodo del reloj de 10 unidades de tiempo
    end

    // Proceso de prueba
    initial begin
        // Inicialización
        rst = 1;
        DIVIDE_BY_N = 4'b1010; // DIVIDE_BY_N = 10
        #10;
        
        // Liberación del reset
        rst = 0;
        
        // Esperar un tiempo para observar las salidas
        #200;

        DIVIDE_BY_N = 4'b0010; // DIVIDE_BY_N = 2
        #200;

        DIVIDE_BY_N = 4'b0100; // DIVIDE_BY_N = 4
        #200;

        DIVIDE_BY_N = 4'b0111; // DIVIDE_BY_N = 7
        #200;
        
        // Terminar la simulación
        $finish;
    end

    // Monitoreo de señales
    initial begin
        $monitor("Time = %0t: clk = %b, rst = %b, DIVIDE_BY_N = %d, comb_out = %b, sync_out = %b", 
                 $time, clk, rst, DIVIDE_BY_N, comb_out, sync_out);
        $dumpfile("pulse_generator_wf.vcd");
        $dumpvars(0, tb_pulse_generator);
    end

endmodule

OpenLane/desings/src/pulse_generator/pulse_generator_wf.vcd
$date
	Tue Jun 11 19:54:57 2024
$end
$version
	Icarus Verilog
$end
$timescale
	1ps
$end
$scope module tb_pulse_generator $end
$var wire 1 ! sync_out $end
$var wire 1 " comb_out $end
$var reg 4 # DIVIDE_BY_N [3:0] $end
$var reg 1 $ clk $end
$var reg 1 % rst $end
$scope module uut $end
$var wire 4 & DIVIDE_BY_N [3:0] $end
$var wire 1 $ clk $end
$var wire 1 % rst $end
$var wire 1 " comb_out $end
$var reg 11 ' count [10:0] $end
$var reg 1 ! sync_out $end
$upscope $end
$upscope $end
$enddefinitions $end
#0
$dumpvars
b0 '
b1010 &
1%
0$
b1010 #
0"
x!
$end
#5000
0!
1$
#10000
0$
0%
#15000
b1 '
1$
#20000
0$
#25000
b10 '
1$
#30000
0$
#35000
b11 '
1$
#40000
0$
#45000
b100 '
1$
#50000
0$
#55000
b101 '
1$
#60000
0$
#65000
b110 '
1$
#70000
0$
#75000
b111 '
1$
#80000
0$
#85000
b1000 '
1$
#90000
0$
#95000
1"
b1001 '
1$
#100000
0$
#105000
0"
b0 '
1!
1$
#110000
0$
#115000
0!
b1 '
1$
#120000
0$
#125000
b10 '
1$
#130000
0$
#135000
b11 '
1$
#140000
0$
#145000
b100 '
1$
#150000
0$
#155000
b101 '
1$
#160000
0$
#165000
b110 '
1$
#170000
0$
#175000
b111 '
1$
#180000
0$
#185000
b1000 '
1$
#190000
0$
#195000
1"
b1001 '
1$
#200000
0$
#205000
0"
b0 '
1!
1$
#210000
0$
b10 #
b10 &
#215000
1"
0!
b1 '
1$
#220000
0$
#225000
0"
b0 '
1!
1$
#230000
0$
#235000
1"
0!
b1 '
1$
#240000
0$
#245000
0"
b0 '
1!
1$
#250000
0$
#255000
1"
0!
b1 '
1$
#260000
0$
#265000
0"
b0 '
1!
1$
#270000
0$
#275000
1"
0!
b1 '
1$
#280000
0$
#285000
0"
b0 '
1!
1$
#290000
0$
#295000
1"
0!
b1 '
1$
#300000
0$
#305000
0"
b0 '
1!
1$
#310000
0$
#315000
1"
0!
b1 '
1$
#320000
0$
#325000
0"
b0 '
1!
1$
#330000
0$
#335000
1"
0!
b1 '
1$
#340000
0$
#345000
0"
b0 '
1!
1$
#350000
0$
#355000
1"
0!
b1 '
1$
#360000
0$
#365000
0"
b0 '
1!
1$
#370000
0$
#375000
1"
0!
b1 '
1$
#380000
0$
#385000
0"
b0 '
1!
1$
#390000
0$
#395000
1"
0!
b1 '
1$
#400000
0$
#405000
0"
b0 '
1!
1$
#410000
0$
b100 #
b100 &
#415000
0!
b1 '
1$
#420000
0$
#425000
b10 '
1$
#430000
0$
#435000
1"
b11 '
1$
#440000
0$
#445000
0"
b0 '
1!
1$
#450000
0$
#455000
0!
b1 '
1$
#460000
0$
#465000
b10 '
1$
#470000
0$
#475000
1"
b11 '
1$
#480000
0$
#485000
0"
b0 '
1!
1$
#490000
0$
#495000
0!
b1 '
1$
#500000
0$
#505000
b10 '
1$
#510000
0$
#515000
1"
b11 '
1$
#520000
0$
#525000
0"
b0 '
1!
1$
#530000
0$
#535000
0!
b1 '
1$
#540000
0$
#545000
b10 '
1$
#550000
0$
#555000
1"
b11 '
1$
#560000
0$
#565000
0"
b0 '
1!
1$
#570000
0$
#575000
0!
b1 '
1$
#580000
0$
#585000
b10 '
1$
#590000
0$
#595000
1"
b11 '
1$
#600000
0$
#605000
0"
b0 '
1!
1$
#610000
0$
b111 #
b111 &
#615000
0!
b1 '
1$
#620000
0$
#625000
b10 '
1$
#630000
0$
#635000
b11 '
1$
#640000
0$
#645000
b100 '
1$
#650000
0$
#655000
b101 '
1$
#660000
0$
#665000
1"
b110 '
1$
#670000
0$
#675000
0"
1!
b0 '
1$
#680000
0$
#685000
b1 '
0!
1$
#690000
0$
#695000
b10 '
1$
#700000
0$
#705000
b11 '
1$
#710000
0$
#715000
b100 '
1$
#720000
0$
#725000
b101 '
1$
#730000
0$
#735000
1"
b110 '
1$
#740000
0$
#745000
0"
b0 '
1!
1$
#750000
0$
#755000
0!
b1 '
1$
#760000
0$
#765000
b10 '
1$
#770000
0$
#775000
b11 '
1$
#780000
0$
#785000
b100 '
1$
#790000
0$
#795000
b101 '
1$
#800000
0$
#805000
1"
b110 '
1$
