OpenLane/testing_designs/signal_generator/forma_distitna.v
module control_signals(
    input wire clk,
    input wire [3:0] max_val,
    output reg phi_p = 0,
    output reg phi_l1 = 0,
    output reg phi_l2 = 0,
    output reg phi_r = 0
);
  	
	//Definimos los contadores a utilizar 
    reg [10:0] count = 0;
  	reg [10:0] count_main = 0;
    reg [12:0] count_phir = 0;
    reg [3:0] max_count = 0;
  	//Seteamos parametros fijos del simulador
  	parameter N = 2;
  	parameter C = 8;
  	parameter P = 64;

    always@(*)begin
        case (max_val)
            
            default: ;
        endcase
    end

    always @(posedge clk) begin
      count <= (count + 1 )% (C*2); // el contador que se encarga de generar phi_l1 phi_l2 y phi_r se incrementa hasta 16 y leugo se reseta a 0
      count_main <= (count_main + 1) ; // este contador es para llevar la cuenta de cuando debe activarse phi_p
      
      	//en este codigo nos aseguramos que phi_r tenga la misma frecuencia que phi_l2 pero distinto DC
        if((count < C / N)) begin
       		phi_r <= 1'b1; 	
        	count_phir = count_phir +1; // contamos cuantas trasnferencias se realizaron
       	end else begin 
       		phi_r <= 1'b0;
       	end
      	
      	// En este bloque se asignan valores para crear phi_l1 y phi_l2
      	if (count < C) begin
            phi_l1 <= 0;
            phi_l2 <= 1;
        end else begin
          	phi_l1 <= 1;
            phi_l2 <= 0;
        end
		
      // En este bloque se asignan valores para crear phi_lp
      if(count_main == (P)) begin
            phi_p <= 1;
	    	count_phir <= 0;
            count_main <= 0;
        	#55; // este delay es para que todas las señales se queden en el valor que tienen miesntras phi_p funcione 
        end else begin
            phi_p <= 0;
        end
		
    end

endmodule

OpenLane/desings/src/signal_generator/control_signals_tb.v
module testbench;
    reg clk;
    reg [3:0] max_val;
    wire phi_p;
    wire phi_l1;
    wire phi_l2;
    wire phi_r;

    // Instancia del módulo signal_generator
    control_signals uut (
        .clk(clk),
        .max_val(max_val),
        .phi_p(phi_p),
        .phi_l1(phi_l1),
        .phi_l2(phi_l2),
        .phi_r(phi_r)
    );

    // Generación del reloj
    initial begin
        clk = 0;
        forever #2 clk = ~clk; // Período de 10 unidades de tiempo
    end

    // Proceso de inicialización
    initial begin
        // Abrir el archivo de salida y habilitar el rastreo
        $dumpfile("control_signals_wf.vcd");
        $dumpvars(0, testbench);

        // Inicializar señales
        max_val = 4'b1111; // Ejemplo de valor máximo
        #1000;

        max_val = 4'b0011; // Cambiar el valor máximo
        #50;

        max_val = 4'b1001; // Cambiar el valor máximo
        #50;

        $finish; // Terminar la simulación
    end

    // Mostrar resultados en cada cambio de reloj
    always @(posedge clk) begin
        $display("Time: %d, max_val: %b, count: %d, phi_p: %b, phi_l1: %b, phi_l2: %b, phi_r: %b",
                 $time, max_val, uut.count, phi_p, phi_l1, phi_l2, phi_r);
    end

endmodule

OpenLane/desings/src/signal_generator/control_signals_wf.vcd
$date
	Mon Jun 10 18:23:09 2024
$end
$version
	Icarus Verilog
$end
$timescale
	1s
$end
$scope module testbench $end
$var wire 1 ! phi_r $end
$var wire 1 " phi_p $end
$var wire 1 # phi_l2 $end
$var wire 1 $ phi_l1 $end
$var reg 1 % clk $end
$var reg 4 & max_val [3:0] $end
$scope module uut $end
$var wire 1 % clk $end
$var wire 4 ' max_val [3:0] $end
$var reg 11 ( count [10:0] $end
$var reg 11 ) count_main [10:0] $end
$var reg 13 * count_phir [12:0] $end
$var reg 4 + max_count [3:0] $end
$var reg 1 $ phi_l1 $end
$var reg 1 # phi_l2 $end
$var reg 1 " phi_p $end
$var reg 1 ! phi_r $end
$upscope $end
$upscope $end
$enddefinitions $end
#0
$dumpvars
b0 +
b0 *
b0 )
b0 (
b1111 '
b1111 &
0%
0$
0#
0"
0!
$end
#2
1#
1!
b1 )
b1 (
b1 *
1%
#4
0%
#6
b10 )
b10 (
b10 *
1%
#8
0%
#10
b11 )
b11 (
b11 *
1%
#12
0%
#14
b100 )
b100 (
b100 *
1%
#16
0%
#18
0!
b101 )
b101 (
1%
#20
0%
#22
b110 )
b110 (
1%
#24
0%
#26
b111 )
b111 (
1%
#28
0%
#30
b1000 )
b1000 (
1%
#32
0%
#34
0#
1$
b1001 )
b1001 (
1%
#36
0%
#38
b1010 )
b1010 (
1%
#40
0%
#42
b1011 )
b1011 (
1%
#44
0%
#46
b1100 )
b1100 (
1%
#48
0%
#50
b1101 )
b1101 (
1%
#52
0%
#54
b1110 )
b1110 (
1%
#56
0%
#58
b1111 )
b1111 (
1%
#60
0%
#62
b10000 )
b0 (
1%
#64
0%
#66
1#
0$
1!
b10001 )
b1 (
b101 *
1%
#68
0%
#70
b10010 )
b10 (
b110 *
1%
#72
0%
#74
b10011 )
b11 (
b111 *
1%
#76
0%
#78
b10100 )
b100 (
b1000 *
1%
#80
0%
#82
0!
b10101 )
b101 (
1%
#84
0%
#86
b10110 )
b110 (
1%
#88
0%
#90
b10111 )
b111 (
1%
#92
0%
#94
b11000 )
b1000 (
1%
#96
0%
#98
0#
1$
b11001 )
b1001 (
1%
#100
0%
#102
b11010 )
b1010 (
1%
#104
0%
#106
b11011 )
b1011 (
1%
#108
0%
#110
b11100 )
b1100 (
1%
#112
0%
#114
b11101 )
b1101 (
1%
#116
0%
#118
b11110 )
b1110 (
1%
#120
0%
#122
b11111 )
b1111 (
1%
#124
0%
#126
b100000 )
b0 (
1%
#128
0%
#130
1#
0$
1!
b100001 )
b1 (
b1001 *
1%
#132
0%
#134
b100010 )
b10 (
b1010 *
1%
#136
0%
#138
b100011 )
b11 (
b1011 *
1%
#140
0%
#142
b100100 )
b100 (
b1100 *
1%
#144
0%
#146
0!
b100101 )
b101 (
1%
#148
0%
#150
b100110 )
b110 (
1%
#152
0%
#154
b100111 )
b111 (
1%
#156
0%
#158
b101000 )
b1000 (
1%
#160
0%
#162
0#
1$
b101001 )
b1001 (
1%
#164
0%
#166
b101010 )
b1010 (
1%
#168
0%
#170
b101011 )
b1011 (
1%
#172
0%
#174
b101100 )
b1100 (
1%
#176
0%
#178
b101101 )
b1101 (
1%
#180
0%
#182
b101110 )
b1110 (
1%
#184
0%
#186
b101111 )
b1111 (
1%
#188
0%
#190
b110000 )
b0 (
1%
#192
0%
#194
1#
0$
1!
b110001 )
b1 (
b1101 *
1%
#196
0%
#198
b110010 )
b10 (
b1110 *
1%
#200
0%
#202
b110011 )
b11 (
b1111 *
1%
#204
0%
#206
b110100 )
b100 (
b10000 *
1%
#208
0%
#210
0!
b110101 )
b101 (
1%
#212
0%
#214
b110110 )
b110 (
1%
#216
0%
#218
b110111 )
b111 (
1%
#220
0%
#222
b111000 )
b1000 (
1%
#224
0%
#226
0#
1$
b111001 )
b1001 (
1%
#228
0%
#230
b111010 )
b1010 (
1%
#232
0%
#234
b111011 )
b1011 (
1%
#236
0%
#238
b111100 )
b1100 (
1%
#240
0%
#242
b111101 )
b1101 (
1%
#244
0%
#246
b111110 )
b1110 (
1%
#248
0%
#250
b111111 )
b1111 (
1%
#252
0%
#254
b1000000 )
b0 (
1%
#256
0%
#258
1"
1#
0$
1!
b0 )
b1 (
b0 *
1%
#260
0%
#262
1%
#264
0%
#266
1%
#268
0%
#270
1%
#272
0%
#274
1%
#276
0%
#278
1%
#280
0%
#282
1%
#284
0%
#286
1%
#288
0%
#290
1%
#292
0%
#294
1%
#296
0%
#298
1%
#300
0%
#302
1%
#304
0%
#306
1%
#308
0%
#310
1%
#312
0%
#314
0"
b1 )
b10 (
b1 *
1%
#316
0%
#318
b10 )
b11 (
b10 *
1%
#320
0%
#322
b11 )
b100 (
b11 *
1%
#324
0%
#326
0!
b100 )
b101 (
1%
#328
0%
#330
b101 )
b110 (
1%
#332
0%
#334
b110 )
b111 (
1%
#336
0%
#338
b111 )
b1000 (
1%
#340
0%
#342
0#
1$
b1000 )
b1001 (
1%
#344
0%
#346
b1001 )
b1010 (
1%
#348
0%
#350
b1010 )
b1011 (
1%
#352
0%
#354
b1011 )
b1100 (
1%
#356
0%
#358
b1100 )
b1101 (
1%
#360
0%
#362
b1101 )
b1110 (
1%
#364
0%
#366
b1110 )
b1111 (
1%
#368
0%
#370
b1111 )
b0 (
1%
#372
0%
#374
1#
0$
1!
b10000 )
b1 (
b100 *
1%
#376
0%
#378
b10001 )
b10 (
b101 *
1%
#380
0%
#382
b10010 )
b11 (
b110 *
1%
#384
0%
#386
b10011 )
b100 (
b111 *
1%
#388
0%
#390
0!
b10100 )
b101 (
1%
#392
0%
#394
b10101 )
b110 (
1%
#396
0%
#398
b10110 )
b111 (
1%
#400
0%
#402
b10111 )
b1000 (
1%
#404
0%
#406
0#
1$
b11000 )
b1001 (
1%
#408
0%
#410
b11001 )
b1010 (
1%
#412
0%
#414
b11010 )
b1011 (
1%
#416
0%
#418
b11011 )
b1100 (
1%
#420
0%
#422
b11100 )
b1101 (
1%
#424
0%
#426
b11101 )
b1110 (
1%
#428
0%
#430
b11110 )
b1111 (
1%
#432
0%
#434
b11111 )
b0 (
1%
#436
0%
#438
1#
0$
1!
b100000 )
b1 (
b1000 *
1%
#440
0%
#442
b100001 )
b10 (
b1001 *
1%
#444
0%
#446
b100010 )
b11 (
b1010 *
1%
#448
0%
#450
b100011 )
b100 (
b1011 *
1%
#452
0%
#454
0!
b100100 )
b101 (
1%
#456
0%
#458
b100101 )
b110 (
1%
#460
0%
#462
b100110 )
b111 (
1%
#464
0%
#466
b100111 )
b1000 (
1%
#468
0%
#470
0#
1$
b101000 )
b1001 (
1%
#472
0%
#474
b101001 )
b1010 (
1%
#476
0%
#478
b101010 )
b1011 (
1%
#480
0%
#482
b101011 )
b1100 (
1%
#484
0%
#486
b101100 )
b1101 (
1%
#488
0%
#490
b101101 )
b1110 (
1%
#492
0%
#494
b101110 )
b1111 (
1%
#496
0%
#498
b101111 )
b0 (
1%
#500
0%
#502
1#
0$
1!
b110000 )
b1 (
b1100 *
1%
#504
0%
#506
b110001 )
b10 (
b1101 *
1%
#508
0%
#510
b110010 )
b11 (
b1110 *
1%
#512
0%
#514
b110011 )
b100 (
b1111 *
1%
#516
0%
#518
0!
b110100 )
b101 (
1%
#520
0%
#522
b110101 )
b110 (
1%
#524
0%
#526
b110110 )
b111 (
1%
#528
0%
#530
b110111 )
b1000 (
1%
#532
0%
#534
0#
1$
b111000 )
b1001 (
1%
#536
0%
#538
b111001 )
b1010 (
1%
#540
0%
#542
b111010 )
b1011 (
1%
#544
0%
#546
b111011 )
b1100 (
1%
#548
0%
#550
b111100 )
b1101 (
1%
#552
0%
#554
b111101 )
b1110 (
1%
#556
0%
#558
b111110 )
b1111 (
1%
#560
0%
#562
b111111 )
b0 (
1%
#564
0%
#566
1#
0$
1!
b1000000 )
b1 (
b10000 *
1%
#568
0%
#570
1"
b0 )
b10 (
b0 *
1%
#572
0%
#574
1%
#576
0%
#578
1%
#580
0%
#582
1%
#584
0%
#586
1%
#588
0%
#590
1%
#592
0%
#594
1%
#596
0%
#598
1%
#600
0%
#602
1%
#604
0%
#606
1%
#608
0%
#610
1%
#612
0%
#614
1%
#616
0%
#618
1%
#620
0%
#622
1%
#624
0%
#626
0"
b1 )
b11 (
b1 *
1%
#628
0%
#630
b10 )
b100 (
b10 *
1%
#632
0%
#634
0!
b11 )
b101 (
1%
#636
0%
#638
b100 )
b110 (
1%
#640
0%
#642
b101 )
b111 (
1%
#644
0%
#646
b110 )
b1000 (
1%
#648
0%
#650
0#
1$
b111 )
b1001 (
1%
#652
0%
#654
b1000 )
b1010 (
1%
#656
0%
#658
b1001 )
b1011 (
1%
#660
0%
#662
b1010 )
b1100 (
1%
#664
0%
#666
b1011 )
b1101 (
1%
#668
0%
#670
b1100 )
b1110 (
1%
#672
0%
#674
b1101 )
b1111 (
1%
#676
0%
#678
b1110 )
b0 (
1%
#680
0%
#682
1#
0$
1!
b1111 )
b1 (
b11 *
1%
#684
0%
#686
b10000 )
b10 (
b100 *
1%
#688
0%
#690
b10001 )
b11 (
b101 *
1%
#692
0%
#694
b10010 )
b100 (
b110 *
1%
#696
0%
#698
0!
b10011 )
b101 (
1%
#700
0%
#702
b10100 )
b110 (
1%
#704
0%
#706
b10101 )
b111 (
1%
#708
0%
#710
b10110 )
b1000 (
1%
#712
0%
#714
0#
1$
b10111 )
b1001 (
1%
#716
0%
#718
b11000 )
b1010 (
1%
#720
0%
#722
b11001 )
b1011 (
1%
#724
0%
#726
b11010 )
b1100 (
1%
#728
0%
#730
b11011 )
b1101 (
1%
#732
0%
#734
b11100 )
b1110 (
1%
#736
0%
#738
b11101 )
b1111 (
1%
#740
0%
#742
b11110 )
b0 (
1%
#744
0%
#746
1#
0$
1!
b11111 )
b1 (
b111 *
1%
#748
0%
#750
b100000 )
b10 (
b1000 *
1%
#752
0%
#754
b100001 )
b11 (
b1001 *
1%
#756
0%
#758
b100010 )
b100 (
b1010 *
1%
#760
0%
#762
0!
b100011 )
b101 (
1%
#764
0%
#766
b100100 )
b110 (
1%
#768
0%
#770
b100101 )
b111 (
1%
#772
0%
#774
b100110 )
b1000 (
1%
#776
0%
#778
0#
1$
b100111 )
b1001 (
1%
#780
0%
#782
b101000 )
b1010 (
1%
#784
0%
#786
b101001 )
b1011 (
1%
#788
0%
#790
b101010 )
b1100 (
1%
#792
0%
#794
b101011 )
b1101 (
1%
#796
0%
#798
b101100 )
b1110 (
1%
#800
0%
#802
b101101 )
b1111 (
1%
#804
0%
#806
b101110 )
b0 (
1%
#808
0%
#810
1#
0$
1!
b101111 )
b1 (
b1011 *
1%
#812
0%
#814
b110000 )
b10 (
b1100 *
1%
#816
0%
#818
b110001 )
b11 (
b1101 *
1%
#820
0%
#822
b110010 )
b100 (
b1110 *
1%
#824
0%
#826
0!
b110011 )
b101 (
1%
#828
0%
#830
b110100 )
b110 (
1%
#832
0%
#834
b110101 )
b111 (
1%
#836
0%
#838
b110110 )
b1000 (
1%
#840
0%
#842
0#
1$
b110111 )
b1001 (
1%
#844
0%
#846
b111000 )
b1010 (
1%
#848
0%
#850
b111001 )
b1011 (
1%
#852
0%
#854
b111010 )
b1100 (
1%
#856
0%
#858
b111011 )
b1101 (
1%
#860
0%
#862
b111100 )
b1110 (
1%
#864
0%
#866
b111101 )
b1111 (
1%
#868
0%
#870
b111110 )
b0 (
1%
#872
0%
#874
1#
0$
1!
b111111 )
b1 (
b1111 *
1%
#876
0%
#878
b1000000 )
b10 (
b10000 *
1%
#880
0%
#882
1"
b0 )
b11 (
b0 *
1%
#884
0%
#886
1%
#888
0%
#890
1%
#892
0%
#894
1%
#896
0%
#898
1%
#900
0%
#902
1%
#904
0%
#906
1%
#908
0%
#910
1%
#912
0%
#914
1%
#916
0%
#918
1%
#920
0%
#922
1%
#924
0%
#926
1%
#928
0%
#930
1%
#932
0%
#934
1%
#936
0%
#938
0"
b1 )
b100 (
b1 *
1%
#940
0%
#942
0!
b10 )
b101 (
1%
#944
0%
#946
b11 )
b110 (
1%
#948
0%
#950
b100 )
b111 (
1%
#952
0%
#954
b101 )
b1000 (
1%
#956
0%
#958
0#
1$
b110 )
b1001 (
1%
#960
0%
#962
b111 )
b1010 (
1%
#964
0%
#966
b1000 )
b1011 (
1%
#968
0%
#970
b1001 )
b1100 (
1%
#972
0%
#974
b1010 )
b1101 (
1%
#976
0%
#978
b1011 )
b1110 (
1%
#980
0%
#982
b1100 )
b1111 (
1%
#984
0%
#986
b1101 )
b0 (
1%
#988
0%
#990
1#
0$
1!
b1110 )
b1 (
b10 *
1%
#992
0%
#994
b1111 )
b10 (
b11 *
1%
#996
0%
#998
b10000 )
b11 (
b100 *
1%
#1000
0%
b11 &
b11 '
#1002
b10001 )
b100 (
b101 *
1%
#1004
0%
#1006
0!
b10010 )
b101 (
1%
#1008
0%
#1010
b10011 )
b110 (
1%
#1012
0%
#1014
b10100 )
b111 (
1%
#1016
0%
#1018
b10101 )
b1000 (
1%
#1020
0%
#1022
0#
1$
b10110 )
b1001 (
1%
#1024
0%
#1026
b10111 )
b1010 (
1%
#1028
0%
#1030
b11000 )
b1011 (
1%
#1032
0%
#1034
b11001 )
b1100 (
1%
#1036
0%
#1038
b11010 )
b1101 (
1%
#1040
0%
#1042
b11011 )
b1110 (
1%
#1044
0%
#1046
b11100 )
b1111 (
1%
#1048
0%
#1050
b11101 )
b0 (
1%
b1001 &
b1001 '
#1052
0%
#1054
1#
0$
1!
b11110 )
b1 (
b110 *
1%
#1056
0%
#1058
b11111 )
b10 (
b111 *
1%
#1060
0%
#1062
b100000 )
b11 (
b1000 *
1%
#1064
0%
#1066
b100001 )
b100 (
b1001 *
1%
#1068
0%
#1070
0!
b100010 )
b101 (
1%
#1072
0%
#1074
b100011 )
b110 (
1%
#1076
0%
#1078
b100100 )
b111 (
1%
#1080
0%
#1082
b100101 )
b1000 (
1%
#1084
0%
#1086
0#
1$
b100110 )
b1001 (
1%
#1088
0%
#1090
b100111 )
b1010 (
1%
#1092
0%
#1094
b101000 )
b1011 (
1%
#1096
0%
#1098
b101001 )
b1100 (
1%
