OpenLane/testing_designs/divisor_prueba/my_divider.v
module my_divider (
  input wire clk_in,     // Señal de reloj de entrada
  input wire reset,      // Señal de reset
  input wire [31:0] div, // Valor del divisor
  output reg clk_out     // Señal de reloj de salida dividida
);

  reg [31:0] counter;

  always @(posedge clk_in or posedge reset) begin
    if (reset) begin
      counter <= 0;
      clk_out <= 0;
    end else begin
      if (counter >= (div - 1)) begin
        counter <= 0;
        clk_out <= ~clk_out; // Cambiar el estado de clk_out
      end else begin
        counter <= counter + 1;
      end
    end
  end

endmodule

OpenLane/desings/src/divisor_prueba/tb_my_divider.v
// Code your testbench here
// or browse Examples
module testbench;
  reg clk_in;
  reg reset;
  reg [31:0] div;
  wire clk_out;

  // Instanciar el divisor de frecuencia
  my_divider uut (
    .clk_in(clk_in),
    .reset(reset),
    .div(div),
    .clk_out(clk_out)
  );

  // instanciar el reloj de entrada con un periodo de 10 unidades de tiempo
    
	initial begin
	  $dumpfile("wf_my_divider.vcd");
          $dumpvars(0, testbench);  // Dump todas las señales de este módulo

    	  clk_in = 0;
        forever #5 clk_in = ~clk_in;
  	end

  initial begin
    // Inicializar las señales
    reset = 1'b1;
    div = 32'd4;  // Valor del divisor

    // Desactivar el reset después de 20 unidades de tiempo
    #20 reset = 0;
    
    // Cambiar el valor de div para probar diferentes divisores
    #100 div = 32'd8;  // División por 8
    #100 div = 32'd16; // División por 16
    #100 div = 32'd32; // División por 32

    // Terminar simulación
    #500 $finish;
  end

  initial begin
    // Monitor para observar los valores
    //$monitor("Time = %0t, clk_in = %b, reset = %b, div = %d, clk_out = %b", 
    //         $time, clk_in, reset, div, clk_out);
  end

endmodule

OpenLane/desings/src/divisor_prueba/wf_my_divider.vcd
$date
	Wed Jun 12 21:53:05 2024
$end
$version
	Icarus Verilog
$end
$timescale
	1s
$end
$scope module testbench $end
$var wire 1 ! clk_out $end
$var reg 1 " clk_in $end
$var reg 32 # div [31:0] $end
$var reg 1 $ reset $end
$scope module uut $end
$var wire 1 " clk_in $end
$var wire 32 % div [31:0] $end
$var wire 1 $ reset $end
$var reg 1 ! clk_out $end
$var reg 32 & counter [31:0] $end
$upscope $end
$upscope $end
$enddefinitions $end
#0
$dumpvars
b0 &
b100 %
1$
b100 #
0"
0!
$end
#5
1"
#10
0"
#15
1"
#20
0"
0$
#25
b1 &
1"
#30
0"
#35
b10 &
1"
#40
0"
#45
b11 &
1"
#50
0"
#55
1!
b0 &
1"
#60
0"
#65
b1 &
1"
#70
0"
#75
b10 &
1"
#80
0"
#85
b11 &
1"
#90
0"
#95
0!
b0 &
1"
#100
0"
#105
b1 &
1"
#110
0"
#115
b10 &
1"
#120
0"
b1000 #
b1000 %
#125
b11 &
1"
#130
0"
#135
b100 &
1"
#140
0"
#145
b101 &
1"
#150
0"
#155
b110 &
1"
#160
0"
#165
b111 &
1"
#170
0"
#175
1!
b0 &
1"
#180
0"
#185
b1 &
1"
#190
0"
#195
b10 &
1"
#200
0"
#205
b11 &
1"
#210
0"
#215
b100 &
1"
#220
0"
b10000 #
b10000 %
#225
b101 &
1"
#230
0"
#235
b110 &
1"
#240
0"
#245
b111 &
1"
#250
0"
#255
b1000 &
1"
#260
0"
#265
b1001 &
1"
#270
0"
#275
b1010 &
1"
#280
0"
#285
b1011 &
1"
#290
0"
#295
b1100 &
1"
#300
0"
#305
b1101 &
1"
#310
0"
#315
b1110 &
1"
#320
0"
b100000 #
b100000 %
#325
b1111 &
1"
#330
0"
#335
b10000 &
1"
#340
0"
#345
b10001 &
1"
#350
0"
#355
b10010 &
1"
#360
0"
#365
b10011 &
1"
#370
0"
#375
b10100 &
1"
#380
0"
#385
b10101 &
1"
#390
0"
#395
b10110 &
1"
#400
0"
#405
b10111 &
1"
#410
0"
#415
b11000 &
1"
#420
0"
#425
b11001 &
1"
#430
0"
#435
b11010 &
1"
#440
0"
#445
b11011 &
1"
#450
0"
#455
b11100 &
1"
#460
0"
#465
b11101 &
1"
#470
0"
#475
b11110 &
1"
#480
0"
#485
b11111 &
1"
#490
0"
#495
0!
b0 &
1"
#500
0"
#505
b1 &
1"
#510
0"
#515
b10 &
1"
#520
0"
#525
b11 &
1"
#530
0"
#535
b100 &
1"
#540
0"
#545
b101 &
1"
#550
0"
#555
b110 &
1"
#560
0"
#565
b111 &
1"
#570
0"
#575
b1000 &
1"
#580
0"
#585
b1001 &
1"
#590
0"
#595
b1010 &
1"
#600
0"
#605
b1011 &
1"
#610
0"
#615
b1100 &
1"
#620
0"
#625
b1101 &
1"
#630
0"
#635
b1110 &
1"
#640
0"
#645
b1111 &
1"
#650
0"
#655
b10000 &
1"
#660
0"
#665
b10001 &
1"
#670
0"
#675
b10010 &
1"
#680
0"
#685
b10011 &
1"
#690
0"
#695
b10100 &
1"
#700
0"
#705
b10101 &
1"
#710
0"
#715
b10110 &
1"
#720
0"
#725
b10111 &
1"
#730
0"
#735
b11000 &
1"
#740
0"
#745
b11001 &
1"
#750
0"
#755
b11010 &
1"
#760
0"
#765
b11011 &
1"
#770
0"
#775
b11100 &
1"
#780
0"
#785
b11101 &
1"
#790
0"
#795
b11110 &
1"
#800
0"
#805
b11111 &
1"
#810
0"
#815
1!
b0 &
1"
