OpenLane/desings/signal_generator/rtl/analog_signal_generator.v
module analog_signal_generator (
    input wire      i_enable,
    input wire      i_phi_l2,
    input wire      i_phi_l1,
    input wire      i_phi_p,
    output wire     o_pixel_flag,
    output wire     o_ADC_frame
);

reg [2:0] contador_flancos;


always @(posedge i_phi_l2 or posedge i_phi_p)begin
    if (~i_enable)
        contador_flancos <= 0;
    else if (i_phi_p)
        contador_flancos <= 0;
    else if (contador_flancos <= 4)
        contador_flancos <= contador_flancos + 1;
end

assign o_pixel_flag = i_phi_l1 && ( contador_flancos == 5 );

assign o_ADC_frame = i_phi_p && i_enable;


endmodule

OpenLane/desings/signal_generator/rtl/tb_analog_signal_generator.v
`timescale 1ns/1ps

module tb_analog_signal_generator;

    // Inputs
    reg i_enable;
    reg i_phi_l2;
    reg i_phi_l1;
    reg i_phi_p;

    // Outputs
    wire pixel_flag;
    wire ADC_frame;

    // Instantiate the Unit Under Test (UUT)
    analog_signal_generator uut (
        .i_enable(i_enable),
        .i_phi_l2(i_phi_l2),
        .i_phi_l1(i_phi_l1),
        .i_phi_p(i_phi_p),
        .o_pixel_flag(pixel_flag),
        .o_ADC_frame(ADC_frame)
    );

    // Clock generation
    initial begin
        i_phi_l2 = 0;
        i_phi_l1 = 1;
        i_phi_p = 0;
        forever #5 i_phi_l2 = ~i_phi_l2; // 10ns period clock
    end

    // Generate i_phi_l1 and i_phi_p signals
    always #5 i_phi_l1 = ~i_phi_l1; // 20ns period clock


    // Stimulus process
    initial begin
        // Initialize Inputs
        i_enable = 0;
        #15; // wait for some time

        // Apply test vectors
        i_enable = 1; #150;
        i_phi_p =1; #15;
        i_phi_p =0; #150;
        i_enable = 0; #20;
        i_enable = 1; #40;

        // Finish simulation after some time
        #200;
        $finish;
    end

    // Monitor the outputs
    initial begin
        $dumpfile("wf_analog_signal_generator.vcd");
        $dumpvars(0, tb_analog_signal_generator);
        $monitor("At time %t, i_enable = %b, i_phi_l2 = %b, i_phi_l1 = %b, i_phi_p = %b, pixel_flag = %b, ADC_frame = %b",
                 $time, i_enable, i_phi_l2, i_phi_l1, i_phi_p, pixel_flag, ADC_frame);
    end

endmodule

OpenLane/desings/signal_generator/rtl/wf_analog_signal_generator.vcd
$date
	Tue Jul 23 20:53:28 2024
$end
$version
	Icarus Verilog
$end
$timescale
	1ps
$end
$scope module tb_analog_signal_generator $end
$var wire 1 ! pixel_flag $end
$var wire 1 " ADC_frame $end
$var reg 1 # i_enable $end
$var reg 1 $ i_phi_l1 $end
$var reg 1 % i_phi_l2 $end
$var reg 1 & i_phi_p $end
$scope module uut $end
$var wire 1 # i_enable $end
$var wire 1 $ i_phi_l1 $end
$var wire 1 % i_phi_l2 $end
$var wire 1 & i_phi_p $end
$var wire 1 " o_ADC_frame $end
$var wire 1 ! o_pixel_flag $end
$var reg 3 ' contador_flancos [2:0] $end
$upscope $end
$upscope $end
$enddefinitions $end
#0
$dumpvars
bx '
0&
0%
1$
0#
0"
x!
$end
#5000
b0 '
0!
0$
1%
#10000
1$
0%
#15000
b1 '
0$
1%
1#
#20000
1$
0%
#25000
b10 '
0$
1%
#30000
1$
0%
#35000
b11 '
0$
1%
#40000
1$
0%
#45000
b100 '
0$
1%
#50000
1$
0%
#55000
b101 '
0$
1%
#60000
1!
1$
0%
#65000
0!
0$
1%
#70000
1!
1$
0%
#75000
0!
0$
1%
#80000
1!
1$
0%
#85000
0!
0$
1%
#90000
1!
1$
0%
#95000
0!
0$
1%
#100000
1!
1$
0%
#105000
0!
0$
1%
#110000
1!
1$
0%
#115000
0!
0$
1%
#120000
1!
1$
0%
#125000
0!
0$
1%
#130000
1!
1$
0%
#135000
0!
0$
1%
#140000
1!
1$
0%
#145000
0!
0$
1%
#150000
1!
1$
0%
#155000
0!
0$
1%
#160000
1!
1$
0%
#165000
b0 '
0!
1"
0$
1%
1&
#170000
1$
0%
#175000
b1 '
0$
1%
#180000
0"
1$
0%
0&
#185000
b10 '
0$
1%
#190000
1$
0%
#195000
b11 '
0$
1%
#200000
1$
0%
#205000
b100 '
0$
1%
#210000
1$
0%
#215000
b101 '
0$
1%
#220000
1!
1$
0%
#225000
0!
0$
1%
#230000
1!
1$
0%
#235000
0!
0$
1%
#240000
1!
1$
0%
#245000
0!
0$
1%
#250000
1!
1$
0%
#255000
0!
0$
1%
#260000
1!
1$
0%
#265000
0!
0$
1%
#270000
1!
1$
0%
#275000
0!
0$
1%
#280000
1!
1$
0%
#285000
0!
0$
1%
#290000
1!
1$
0%
#295000
0!
0$
1%
#300000
1!
1$
0%
#305000
0!
0$
1%
#310000
1!
1$
0%
#315000
0!
0$
1%
#320000
1!
1$
0%
#325000
0!
0$
1%
#330000
1!
1$
0%
0#
#335000
b0 '
0!
0$
1%
#340000
1$
0%
#345000
0$
1%
#350000
1$
0%
1#
#355000
b1 '
0$
1%
#360000
1$
0%
#365000
b10 '
0$
1%
#370000
1$
0%
#375000
b11 '
0$
1%
#380000
1$
0%
#385000
b100 '
0$
1%
#390000
1$
0%
#395000
b101 '
0$
1%
#400000
1!
1$
0%
#405000
0!
0$
1%
#410000
1!
1$
0%
#415000
0!
0$
1%
#420000
1!
1$
0%
#425000
0!
0$
1%
#430000
1!
1$
0%
#435000
0!
0$
1%
#440000
1!
1$
0%
#445000
0!
0$
1%
#450000
1!
1$
0%
#455000
0!
0$
1%
#460000
1!
1$
0%
#465000
0!
0$
1%
#470000
1!
1$
0%
#475000
0!
0$
1%
#480000
1!
1$
0%
#485000
0!
0$
1%
#490000
1!
1$
0%
#495000
0!
0$
1%
#500000
1!
1$
0%
#505000
0!
0$
1%
#510000
1!
1$
0%
#515000
0!
0$
1%
#520000
1!
1$
0%
#525000
0!
0$
1%
#530000
1!
1$
0%
#535000
0!
0$
1%
#540000
1!
1$
0%
#545000
0!
0$
1%
#550000
1!
1$
0%
#555000
0!
0$
1%
#560000
1!
1$
0%
#565000
0!
0$
1%
#570000
1!
1$
0%
#575000
0!
0$
1%
#580000
1!
1$
0%
#585000
0!
0$
1%
#590000
1!
1$
0%
